<?xml version="1.0" encoding="UTF-8"?><nfeProc versao="4.00" xmlns="http://www.portalfiscal.inf.br/nfe"><protNFe><infProt><nProt>243250028319305</nProt><digVal>tZM7IOAu4UozbarCZ9UZUbEFGT4=</digVal><dhRecbto>2025-01-29T12:10:51-03:00</dhRecbto><chNFe>43250194696242000105550020000181221007365891</chNFe><xMotivo>Autorizado o uso da NF-e</xMotivo><cStat>100</cStat></infProt></protNFe><NFe><infNFe Id="NFe43250194696242000105550020000181221007365891" versao="4.00"><infAdic><infCpl>Diferimento Parcial conforme RICMS Livro III Art. 1 K.|ATENCAO CLIENTE: E sua responsabilidade a emissao da Contra Nota ou Manifestacao do destinatario sobre a Ciencia da Operacao, encaminhar por email!|OC: 023556,119561,119655,119812|; Fonte do valor aproximado dos Tributos: IBPT</infCpl></infAdic><det><nItem>1</nItem><prod><xPed>023556</xPed><cEAN>SEM GTIN</cEAN><cProd>13778-1</cProd><qCom>164.0000</qCom><cEANTrib>SEM GTIN</cEANTrib><vUnTrib>5.8790000000</vUnTrib><qTrib>164.0000</qTrib><vProd>964.16</vProd><xProd>CAIXA 0010B/05784</xProd><vUnCom>5.8790000000</vUnCom><nItemPed>0</nItemPed><indTot>1</indTot><uTrib>UN</uTrib><NCM>48191000</NCM><uCom>UN</uCom><CFOP>5101</CFOP></prod><imposto><vTotTrib>329.07</vTotTrib><ICMS><ICMS51><modBC>3</modBC><vICMSDif>48.21</vICMSDif><vICMSOp>163.91</vICMSOp><pDif>29.4118</pDif><pRedBC>0.0000</pRedBC><orig>0</orig><CST>51</CST><vBC>964.16</vBC><vICMS>115.70</vICMS><pICMS>17.0000</pICMS></ICMS51></ICMS><IPI><cEnq>999</cEnq><IPITrib><CST>50</CST><vBC>964.16</vBC><pIPI>15.0000</pIPI><vIPI>144.62</vIPI></IPITrib></IPI><COFINS><COFINSAliq><vCOFINS>25.45</vCOFINS><CST>01</CST><vBC>848.46</vBC><pCOFINS>3.0000</pCOFINS></COFINSAliq></COFINS><PIS><PISAliq><vPIS>5.51</vPIS><CST>01</CST><vBC>848.46</vBC><pPIS>0.6500</pPIS></PISAliq></PIS></imposto><infAdProd>OC 023556</infAdProd></det><det><nItem>2</nItem><prod><xPed>023556</xPed><cEAN>SEM GTIN</cEAN><cProd>17663-1</cProd><qCom>498.0000</qCom><cEANTrib>SEM GTIN</cEANTrib><vUnTrib>6.0210000000</vUnTrib><qTrib>498.0000</qTrib><vProd>2998.46</vProd><xProd>CAIXA 4115/26544</xProd><vUnCom>6.0210000000</vUnCom><nItemPed>0</nItemPed><indTot>1</indTot><uTrib>UN</uTrib><NCM>48191000</NCM><uCom>UN</uCom><CFOP>5101</CFOP></prod><imposto><vTotTrib>1023.37</vTotTrib><ICMS><ICMS51><modBC>3</modBC><vICMSDif>149.92</vICMSDif><vICMSOp>509.74</vICMSOp><pDif>29.4118</pDif><pRedBC>0.0000</pRedBC><orig>0</orig><CST>51</CST><vBC>2998.46</vBC><vICMS>359.82</vICMS><pICMS>17.0000</pICMS></ICMS51></ICMS><IPI><cEnq>999</cEnq><IPITrib><CST>50</CST><vBC>2998.46</vBC><pIPI>15.0000</pIPI><vIPI>449.77</vIPI></IPITrib></IPI><COFINS><COFINSAliq><vCOFINS>79.16</vCOFINS><CST>01</CST><vBC>2638.64</vBC><pCOFINS>3.0000</pCOFINS></COFINSAliq></COFINS><PIS><PISAliq><vPIS>17.15</vPIS><CST>01</CST><vBC>2638.64</vBC><pPIS>0.6500</pPIS></PISAliq></PIS></imposto><infAdProd>OC 023556</infAdProd></det><det><nItem>3</nItem><prod><xPed>119812</xPed><cEAN>SEM GTIN</cEAN><cProd>17628-1</cProd><qCom>1451.0000</qCom><cEANTrib>SEM GTIN</cEANTrib><vUnTrib>0.5950000000</vUnTrib><qTrib>1451.0000</qTrib><vProd>863.35</vProd><xProd>ACESS. 1210/26525</xProd><vUnCom>0.5950000000</vUnCom><nItemPed>0</nItemPed><indTot>1</indTot><uTrib>UN</uTrib><NCM>48239099</NCM><uCom>UN</uCom><CFOP>5101</CFOP></prod><imposto><vTotTrib>294.66</vTotTrib><ICMS><ICMS51><modBC>3</modBC><vICMSDif>43.17</vICMSDif><vICMSOp>146.77</vICMSOp><pDif>29.4118</pDif><pRedBC>0.0000</pRedBC><orig>0</orig><CST>51</CST><vBC>863.35</vBC><vICMS>103.60</vICMS><pICMS>17.0000</pICMS></ICMS51></ICMS><IPI><cEnq>999</cEnq><IPITrib><CST>50</CST><vBC>863.35</vBC><pIPI>9.7500</pIPI><vIPI>84.18</vIPI></IPITrib></IPI><COFINS><COFINSAliq><vCOFINS>22.79</vCOFINS><CST>01</CST><vBC>759.75</vBC><pCOFINS>3.0000</pCOFINS></COFINSAliq></COFINS><PIS><PISAliq><vPIS>4.94</vPIS><CST>01</CST><vBC>759.75</vBC><pPIS>0.6500</pPIS></PISAliq></PIS></imposto><infAdProd>OC 119812</infAdProd></det><det><nItem>4</nItem><prod><xPed>119812</xPed><cEAN>SEM GTIN</cEAN><cProd>17627-1</cProd><qCom>2185.0000</qCom><cEANTrib>SEM GTIN</cEANTrib><vUnTrib>0.4010000000</vUnTrib><qTrib>2185.0000</qTrib><vProd>876.19</vProd><xProd>ACESS. 1210/26526</xProd><vUnCom>0.4010000000</vUnCom><nItemPed>0</nItemPed><indTot>1</indTot><uTrib>UN</uTrib><NCM>48239099</NCM><uCom>UN</uCom><CFOP>5101</CFOP></prod><imposto><vTotTrib>299.04</vTotTrib><ICMS><ICMS51><modBC>3</modBC><vICMSDif>43.81</vICMSDif><vICMSOp>148.95</vICMSOp><pDif>29.4118</pDif><pRedBC>0.0000</pRedBC><orig>0</orig><CST>51</CST><vBC>876.19</vBC><vICMS>105.14</vICMS><pICMS>17.0000</pICMS></ICMS51></ICMS><IPI><cEnq>999</cEnq><IPITrib><CST>50</CST><vBC>876.19</vBC><pIPI>9.7500</pIPI><vIPI>85.43</vIPI></IPITrib></IPI><COFINS><COFINSAliq><vCOFINS>23.13</vCOFINS><CST>01</CST><vBC>771.05</vBC><pCOFINS>3.0000</pCOFINS></COFINSAliq></COFINS><PIS><PISAliq><vPIS>5.01</vPIS><CST>01</CST><vBC>771.05</vBC><pPIS>0.6500</pPIS></PISAliq></PIS></imposto><infAdProd>OC 119812</infAdProd></det><det><nItem>5</nItem><prod><xPed>119655</xPed><cEAN>SEM GTIN</cEAN><cProd>17950-1</cProd><qCom>3113.0000</qCom><cEANTrib>SEM GTIN</cEANTrib><vUnTrib>0.3770000000</vUnTrib><qTrib>3113.0000</qTrib><vProd>1173.60</vProd><xProd>ACESS. 1211/30496</xProd><vUnCom>0.3770000000</vUnCom><nItemPed>0</nItemPed><indTot>1</indTot><uTrib>UN</uTrib><NCM>48239099</NCM><uCom>UN</uCom><CFOP>5101</CFOP></prod><imposto><vTotTrib>400.55</vTotTrib><ICMS><ICMS51><modBC>3</modBC><vICMSDif>58.68</vICMSDif><vICMSOp>199.51</vICMSOp><pDif>29.4118</pDif><pRedBC>0.0000</pRedBC><orig>0</orig><CST>51</CST><vBC>1173.60</vBC><vICMS>140.83</vICMS><pICMS>17.0000</pICMS></ICMS51></ICMS><IPI><cEnq>999</cEnq><IPITrib><CST>50</CST><vBC>1173.60</vBC><pIPI>9.7500</pIPI><vIPI>114.43</vIPI></IPITrib></IPI><COFINS><COFINSAliq><vCOFINS>30.98</vCOFINS><CST>01</CST><vBC>1032.77</vBC><pCOFINS>3.0000</pCOFINS></COFINSAliq></COFINS><PIS><PISAliq><vPIS>6.71</vPIS><CST>01</CST><vBC>1032.77</vBC><pPIS>0.6500</pPIS></PISAliq></PIS></imposto><infAdProd>OC 119655</infAdProd></det><det><nItem>6</nItem><prod><xPed>119561</xPed><cEAN>SEM GTIN</cEAN><cProd>18815-1</cProd><qCom>1850.0000</qCom><cEANTrib>SEM GTIN</cEANTrib><vUnTrib>5.8400000000</vUnTrib><qTrib>1850.0000</qTrib><vProd>10804.00</vProd><xProd>CAIXA 1212/31228 ABA SUP 40MM</xProd><vUnCom>5.8400000000</vUnCom><nItemPed>0</nItemPed><indTot>1</indTot><uTrib>UN</uTrib><NCM>48191000</NCM><uCom>UN</uCom><CFOP>5101</CFOP></prod><imposto><vTotTrib>3687.41</vTotTrib><ICMS><ICMS51><modBC>3</modBC><vICMSDif>540.20</vICMSDif><vICMSOp>1836.68</vICMSOp><pDif>29.4118</pDif><pRedBC>0.0000</pRedBC><orig>0</orig><CST>51</CST><vBC>10804.00</vBC><vICMS>1296.48</vICMS><pICMS>17.0000</pICMS></ICMS51></ICMS><IPI><cEnq>999</cEnq><IPITrib><CST>50</CST><vBC>10804.00</vBC><pIPI>15.0000</pIPI><vIPI>1620.60</vIPI></IPITrib></IPI><COFINS><COFINSAliq><vCOFINS>285.23</vCOFINS><CST>01</CST><vBC>9507.52</vBC><pCOFINS>3.0000</pCOFINS></COFINSAliq></COFINS><PIS><PISAliq><vPIS>61.80</vPIS><CST>01</CST><vBC>9507.52</vBC><pPIS>0.6500</pPIS></PISAliq></PIS></imposto><infAdProd>OC 119561</infAdProd></det><total><ICMSTot><vCOFINS>466.74</vCOFINS><vBCST>0.00</vBCST><vICMSDeson>0.00</vICMSDeson><vProd>17679.76</vProd><vSeg>0.00</vSeg><vFCP>0.00</vFCP><vFCPST>0.00</vFCPST><vNF>20178.79</vNF><vTotTrib>6034.10</vTotTrib><vPIS>101.12</vPIS><vIPIDevol>0.00</vIPIDevol><vBC>17679.76</vBC><vST>0.00</vST><vICMS>2121.57</vICMS><vII>0.00</vII><vFCPSTRet>0.00</vFCPSTRet><vDesc>0.00</vDesc><vOutro>0.00</vOutro><vIPI>2499.03</vIPI><vFrete>0.00</vFrete></ICMSTot></total><cobr><fat><vOrig>20178.79</vOrig><nFat>18122</nFat><vDesc>0.00</vDesc><vLiq>20178.79</vLiq></fat><dup><dVenc>2025-02-19</dVenc><nDup>001</nDup><vDup>20178.79</vDup></dup></cobr><pag><detPag><vPag>20178.79</vPag><tPag>15</tPag><indPag>1</indPag></detPag></pag><Id>NFe43250194696242000105550020000181221007365891</Id><ide><tpNF>1</tpNF><mod>55</mod><indPres>0</indPres><tpImp>1</tpImp><nNF>18122</nNF><cMunFG>4303103</cMunFG><procEmi>0</procEmi><finNFe>1</finNFe><dhEmi>2025-01-29T12:10:35-03:00</dhEmi><tpAmb>1</tpAmb><indFinal>0</indFinal><idDest>1</idDest><tpEmis>1</tpEmis><cDV>1</cDV><cUF>43</cUF><serie>2</serie><natOp>VENDA DE PROD. PROPRIA - Comercializacao/Industrializacao</natOp><cNF>00736589</cNF><verProc>ACBrNFe</verProc></ide><emit><xNome>TRES DESIGN E EMBALAGENS LTDA</xNome><CRT>3</CRT><xFant>TRES EMBALAGENS</xFant><CNPJ>94696242000105</CNPJ><enderEmit><xCpl>BLOCO 1 FR</xCpl><fone>5133443434</fone><UF>RS</UF><xPais>Brasil</xPais><cPais>1058</cPais><xLgr>RUA FREDERICO AUGUSTO RITTER</xLgr><xMun>CACHOERINHA</xMun><nro>4905</nro><cMun>4303103</cMun><xBairro>DISTRITO INDL</xBairro><CEP>94931001</CEP></enderEmit><IE>1770207314</IE></emit><dest><xNome>TERMOLAR S/A</xNome><CNPJ>92780634000122</CNPJ><enderDest><fone>5121218000</fone><UF>RS</UF><xPais>BRASIL</xPais><cPais>1058</cPais><xLgr>RUA TAMANDARE</xLgr><xMun>PORTO ALEGRE</xMun><nro>500</nro><cMun>4314902</cMun><xBairro>CRISTAL</xBairro><CEP>91900790</CEP></enderDest><IE>0960219285</IE><indIEDest>1</indIEDest><email>recebimento@termolar.com.br</email></dest><transp><modFrete>0</modFrete><vol><pesoL>932.000</pesoL><qVol>170</qVol><pesoB>932.000</pesoB></vol></transp></infNFe></NFe><versao>4.00</versao></nfeProc>